llm_tools_server/__init__.py
llm_tools_server/backends.py
llm_tools_server/builtin_tools.py
llm_tools_server/config.py
llm_tools_server/server.py
llm_tools_server/web_search_tool.py
llm_tools_server/webui.py
llm_tools_server/eval/README.md
llm_tools_server/eval/__init__.py
llm_tools_server/eval/evaluator.py
llm_tools_server/eval/rag_evaluator.py
llm_tools_server/eval/rag_test_builder.py
llm_tools_server/eval/rag_test_case.py
llm_tools_server/eval/reporters.py
llm_tools_server/eval/test_case.py
llm_tools_server/eval/validators.py
llm_tools_server/rag/__init__.py
llm_tools_server/rag/chunker.py
llm_tools_server/rag/config.py
llm_tools_server/rag/contextualizer.py
llm_tools_server/rag/crawler.py
llm_tools_server/rag/indexer.py
llm_tools_server/rag/updater.py
llm_tools_server-0.12.1.dist-info/METADATA
llm_tools_server-0.12.1.dist-info/WHEEL
llm_tools_server-0.12.1.dist-info/top_level.txt
llm_tools_server-0.12.1.dist-info/RECORD
