Metadata-Version: 2.4
Name: llm-tools-server
Version: 0.12.1
Summary: Reusable Flask server for LLM backends (Ollama, LM Studio) with tool calling
Author: LLM API Server Contributors
Project-URL: Homepage, https://github.com/assareh/llm-tools-server
Project-URL: Repository, https://github.com/assareh/llm-tools-server
Project-URL: Issues, https://github.com/assareh/llm-tools-server/issues
Keywords: llm,openai,api,flask,ollama,lmstudio,tools
Classifier: Development Status :: 3 - Alpha
Classifier: Intended Audience :: Developers
Classifier: License :: OSI Approved :: MIT License
Classifier: Topic :: Software Development :: Libraries :: Application Frameworks
Classifier: Programming Language :: Python :: 3
Classifier: Programming Language :: Python :: 3.11
Classifier: Programming Language :: Python :: 3.12
Requires-Python: >=3.11
Requires-Dist: flask>=3.0.0
Requires-Dist: flask-cors>=4.0.0
Requires-Dist: requests>=2.31.0
Requires-Dist: python-dotenv>=1.0.0
Requires-Dist: langchain-core>=0.1.0
Provides-Extra: webui
Requires-Dist: open-webui; extra == "webui"
Provides-Extra: websearch
Provides-Extra: eval
Requires-Dist: markdown>=3.5.0; extra == "eval"
Provides-Extra: rag
Requires-Dist: langchain>=0.3.0; extra == "rag"
Requires-Dist: langchain-community>=0.0.13; extra == "rag"
Requires-Dist: langchain-huggingface>=0.3.0; extra == "rag"
Requires-Dist: langchain-text-splitters>=0.3.0; extra == "rag"
Requires-Dist: faiss-cpu>=1.8.0; extra == "rag"
Requires-Dist: sentence-transformers>=2.3.0; extra == "rag"
Requires-Dist: beautifulsoup4>=4.12.0; extra == "rag"
Requires-Dist: tiktoken>=0.5.0; extra == "rag"
Requires-Dist: rank-bm25>=0.2.2; extra == "rag"
Requires-Dist: trafilatura>=2.0.0; extra == "rag"
Requires-Dist: tqdm>=4.65.0; extra == "rag"
Provides-Extra: dev
Requires-Dist: pytest; extra == "dev"
Requires-Dist: pytest-mock; extra == "dev"
Requires-Dist: black; extra == "dev"
Requires-Dist: ruff; extra == "dev"
Requires-Dist: mypy; extra == "dev"
